duoyuantongji/__init__.py
duoyuantongji/classify.py
duoyuantongji/corrcoef.py
duoyuantongji/example.py
duoyuantongji/k_means.py
duoyuantongji/labels.py
duoyuantongji/linear_predict.py
duoyuantongji/pca.py
duoyuantongji/vals_vectors.py
duoyuantongji-1.0.0.dist-info/METADATA
duoyuantongji-1.0.0.dist-info/WHEEL
duoyuantongji-1.0.0.dist-info/licenses/LICENSE
duoyuantongji-1.0.0.dist-info/RECORD
