Metadata-Version: 2.1
Name: duoyuantongji
Version: 1.0.0
Summary: A small example package
Project-URL: Homepage, https://github.com/moudexiao
Project-URL: Bug Tracker, https://github.com/moudexiao/duoyuantongji/issues
Author-email: sudragin <2017614231@qq.com>
License-File: LICENSE
Classifier: License :: OSI Approved :: MIT License
Classifier: Operating System :: OS Independent
Classifier: Programming Language :: Python :: 3
Requires-Python: >=3.7
Requires-Dist: numpy
Requires-Dist: scikit-learn
